tencentcloud/__init__.py
tencentcloud/dts/__init__.py
tencentcloud/dts/v20180330/__init__.py
tencentcloud/dts/v20180330/dts_client.py
tencentcloud/dts/v20180330/dts_client_async.py
tencentcloud/dts/v20180330/errorcodes.py
tencentcloud/dts/v20180330/models.py
tencentcloud/dts/v20211206/__init__.py
tencentcloud/dts/v20211206/dts_client.py
tencentcloud/dts/v20211206/dts_client_async.py
tencentcloud/dts/v20211206/errorcodes.py
tencentcloud/dts/v20211206/models.py
tencentcloud_sdk_python_dts-3.1.7.dist-info/METADATA
tencentcloud_sdk_python_dts-3.1.7.dist-info/WHEEL
tencentcloud_sdk_python_dts-3.1.7.dist-info/top_level.txt
tencentcloud_sdk_python_dts-3.1.7.dist-info/RECORD
